mindtrace/database/__init__.py
mindtrace/database/backends/mindtrace_odm.py
mindtrace/database/backends/mongo_odm.py
mindtrace/database/backends/redis_odm.py
mindtrace/database/backends/registry_odm.py
mindtrace/database/backends/unified_odm.py
mindtrace/database/core/exceptions.py
mindtrace/database/sample/user.py
mindtrace_database-0.8.0.dist-info/licenses/LICENSE
mindtrace_database-0.8.0.dist-info/METADATA
mindtrace_database-0.8.0.dist-info/WHEEL
mindtrace_database-0.8.0.dist-info/top_level.txt
mindtrace_database-0.8.0.dist-info/RECORD
