Metadata-Version: 2.4
Name: mindtrace-database
Version: 0.8.0
Summary: Database functionality for Mindtrace
Author: Mindtrace Team
License-Expression: Apache-2.0
Project-URL: Homepage, https://mindtrace.ai
Project-URL: Repository, https://github.com/mindtrace/mindtrace/blob/main/mindtrace/database
Classifier: Programming Language :: Python :: 3
Classifier: Programming Language :: Python :: 3.12
License-File: LICENSE
Requires-Dist: beanie<2,>=1.29.0
Requires-Dist: mindtrace-core>=0.8.0
Requires-Dist: pydantic>=2.11.1
Requires-Dist: redis>=4.0.0
Requires-Dist: redis-om>=0.3.5
Requires-Dist: motor>=3.3.0
Requires-Dist: pymongo>=4.14.0
Requires-Dist: mindtrace-registry>=0.8.0
Dynamic: license-file
